ChemScraper/__init__.py
ChemScraper/schema.py
ChemScraper/settings.py
ChemScraper/pubchem/__init__.py
ChemScraper/pubchem/entrez.py
ChemScraper/pubchem/gateway.py
ChemScraper/pubchem/view.py
ChemScraper/utils/__init__.py
ChemScraper/utils/file.py
ChemScraper/utils/general.py
ChemScraper/utils/mol.py
ChemScraper/vscraper/__init__.py
ChemScraper/vscraper/se.py
ChemScraper/vscraper/sigma_aldrich.py
ChemScraper/vscraper/thermo_fisher.py
ChemScraper-0.2.dist-info/LICENSE
ChemScraper-0.2.dist-info/METADATA
ChemScraper-0.2.dist-info/WHEEL
ChemScraper-0.2.dist-info/top_level.txt
ChemScraper-0.2.dist-info/RECORD
