Metadata-Version: 2.1
Name: ChemScraper
Version: 0.2
Summary: Scraping chemical vendors for pricing/availability info.
Author-email: qianxiang ai <qai1@fordham.edu>
License: MIT License        
Project-URL: Homepage, https://github.com/qai222/ChemScraper
Classifier: Programming Language :: Python :: 3
Classifier: License :: OSI Approved :: MIT License
Classifier: Operating System :: OS Independent
Requires-Python: >=3.9
License-File: LICENSE
Requires-Dist: argon2-cffi (==21.3.0)
Requires-Dist: argon2-cffi-bindings (==21.2.0)
Requires-Dist: asttokens (==2.0.5)
Requires-Dist: async-generator (==1.10)
Requires-Dist: attrs (==22.1.0)
Requires-Dist: backcall (==0.2.0)
Requires-Dist: beautifulsoup4 (==4.11.1)
Requires-Dist: bleach (==5.0.1)
Requires-Dist: certifi (==2022.6.15)
Requires-Dist: cffi (==1.15.1)
Requires-Dist: charset-normalizer (==2.1.0)
Requires-Dist: colorama (==0.4.5)
Requires-Dist: cryptography (==37.0.4)
Requires-Dist: debugpy (==1.6.2)
Requires-Dist: decorator (==5.1.1)
Requires-Dist: defusedxml (==0.7.1)
Requires-Dist: entrypoints (==0.4)
Requires-Dist: executing (==0.9.1)
Requires-Dist: fake-useragent (==0.1.11)
Requires-Dist: fastjsonschema (==2.16.1)
Requires-Dist: h11 (==0.13.0)
Requires-Dist: idna (==3.3)
Requires-Dist: ipykernel (==6.15.1)
Requires-Dist: ipython (==8.4.0)
Requires-Dist: ipython-genutils (==0.2.0)
Requires-Dist: ipywidgets (==7.7.1)
Requires-Dist: jedi (==0.18.1)
Requires-Dist: Jinja2 (==3.1.2)
Requires-Dist: jsonschema (==4.9.1)
Requires-Dist: jupyter (==1.0.0)
Requires-Dist: jupyter-client (==7.3.4)
Requires-Dist: jupyter-console (==6.4.4)
Requires-Dist: jupyter-core (==4.11.1)
Requires-Dist: jupyterlab-pygments (==0.2.2)
Requires-Dist: jupyterlab-widgets (==1.1.1)
Requires-Dist: loguru (==0.6.0)
Requires-Dist: MarkupSafe (==2.1.1)
Requires-Dist: matplotlib-inline (==0.1.3)
Requires-Dist: mistune (==0.8.4)
Requires-Dist: monty (==2022.4.26)
Requires-Dist: nbclient (==0.6.6)
Requires-Dist: nbconvert (==6.5.0)
Requires-Dist: nbformat (==5.4.0)
Requires-Dist: nest-asyncio (==1.5.5)
Requires-Dist: notebook (==6.4.12)
Requires-Dist: numpy (==1.23.1)
Requires-Dist: outcome (==1.2.0)
Requires-Dist: packaging (==21.3)
Requires-Dist: pandas (==1.4.3)
Requires-Dist: pandocfilters (==1.5.0)
Requires-Dist: parso (==0.8.3)
Requires-Dist: pickleshare (==0.7.5)
Requires-Dist: Pillow (==9.2.0)
Requires-Dist: prometheus-client (==0.14.1)
Requires-Dist: prompt-toolkit (==3.0.30)
Requires-Dist: psutil (==5.9.1)
Requires-Dist: pure-eval (==0.2.2)
Requires-Dist: pycparser (==2.21)
Requires-Dist: Pygments (==2.12.0)
Requires-Dist: pyOpenSSL (==22.0.0)
Requires-Dist: pyparsing (==3.0.9)
Requires-Dist: pyrsistent (==0.18.1)
Requires-Dist: PySocks (==1.7.1)
Requires-Dist: python-dateutil (==2.8.2)
Requires-Dist: python-dotenv (==0.20.0)
Requires-Dist: pytz (==2022.1)
Requires-Dist: pywin32 (==304)
Requires-Dist: pywinpty (==2.0.7)
Requires-Dist: pyzmq (==23.2.0)
Requires-Dist: qtconsole (==5.3.1)
Requires-Dist: QtPy (==2.1.0)
Requires-Dist: ratelimit (==2.2.1)
Requires-Dist: rdkit (==2022.3.4)
Requires-Dist: requests (==2.28.1)
Requires-Dist: selenium (==4.3.0)
Requires-Dist: Send2Trash (==1.8.0)
Requires-Dist: six (==1.16.0)
Requires-Dist: sniffio (==1.2.0)
Requires-Dist: sortedcontainers (==2.4.0)
Requires-Dist: soupsieve (==2.3.2.post1)
Requires-Dist: stack-data (==0.3.0)
Requires-Dist: terminado (==0.15.0)
Requires-Dist: tinycss2 (==1.1.1)
Requires-Dist: tornado (==6.2)
Requires-Dist: tqdm (==4.64.0)
Requires-Dist: traitlets (==5.3.0)
Requires-Dist: trio (==0.21.0)
Requires-Dist: trio-websocket (==0.9.2)
Requires-Dist: urllib3 (==1.26.11)
Requires-Dist: wcwidth (==0.2.5)
Requires-Dist: webdriver-manager (==3.8.3)
Requires-Dist: webencodings (==0.5.1)
Requires-Dist: widgetsnbextension (==3.6.1)
Requires-Dist: win32-setctime (==1.1.0)
Requires-Dist: wsproto (==1.1.0)
